LICENSE
README.rst
pyproject.toml
setup.py
aiointeractions/__init__.py
aiointeractions/app.py
aiointeractions.egg-info/PKG-INFO
aiointeractions.egg-info/SOURCES.txt
aiointeractions.egg-info/dependency_links.txt
aiointeractions.egg-info/requires.txt
aiointeractions.egg-info/top_level.txt
tests/test_interactions_handler.py
tests/test_running.py