Metadata-Version: 2.1
Name: aiointeractions
Version: 1.2.3
Summary: An async Discord HTTP Interactions wrapper for discord.py.
Author: The Master
License: MIT
Project-URL: Homepage, http://github.com/TheMaster3558/aiointeractions
Project-URL: Documentation, http://aiointeractions.readthedocs.io/
Keywords: discord
Classifier: Development Status :: 5 - Production/Stable
Classifier: License :: OSI Approved :: MIT License
Classifier: Intended Audience :: Developers
Classifier: Natural Language :: English
Classifier: Operating System :: OS Independent
Classifier: Programming Language :: Python :: 3.8
Classifier: Programming Language :: Python :: 3.9
Classifier: Programming Language :: Python :: 3.10
Classifier: Programming Language :: Python :: 3.11
Classifier: Topic :: Internet
Classifier: Topic :: Software Development :: Libraries
Classifier: Topic :: Software Development :: Libraries :: Python Modules
Classifier: Topic :: Utilities
Classifier: Typing :: Typed
Requires-Python: >=3.8
Provides-Extra: docs
Provides-Extra: tests
License-File: LICENSE
